{
  "targets": [
    "swap",
    "previous"
  ],
  "passes": [
    {
      "name": "genshinui:rounded_rect_fill",
      "intarget": "minecraft:main",
      "outtarget": "swap",
      "auxtargets": [
        {
          "name": "PrevSampler",
          "id": "previous"
        }
      ],
      "uniforms": [
        {
          "name": "Radius",
          "values": [50.0]
        },
        {
          "name": "Center1",
          "values": [0.0, 0.0]
        },
        {
          "name": "Center2",
          "values": [100.0, 100.0]
        }
      ]
    },
    {
      "name": "blit",
      "intarget": "swap",
      "outtarget": "previous"
    },
    {
      "name": "blit",
      "intarget": "swap",
      "outtarget": "minecraft:main"
    }
  ]
}