{
    "providers": [
        {
            "type": "caxton",
            "regular": {
                "file": "genshinui:custom.ttf",
                "shadow_offset": 0.5,
                "scale_factor": 1.0
            },
            "bold": {
                "file": "genshinui:custom.ttf",
                "shadow_offset": 0.5,
                "scale_factor": 1.0
            },
            "italic": {
                "file": "genshinui:custom.ttf",
                "shadow_offset": 0.5,
                "scale_factor": 1.0
            },
            "bold_italic": {
                "file": "genshinui:custom.ttf",
                "shadow_offset": 0.5,
                "scale_factor": 1.0
            }
        }
    ]
}